nestling_app/__init__.py
nestling_app/api/__init__.py
nestling_app/api/app.py
nestling_app/api/graph_export.png
nestling_app/api/translations.py
nestling_app/api/assets/logo.png
nestling_app/api/assets/nestlings.jpg
nestling_app/api/assets/ngapp_log.png
nestling_app/models/__init__.py
nestling_app/models/growth_models.py
nestling_growth_app-0.1.10.dist-info/METADATA
nestling_growth_app-0.1.10.dist-info/WHEEL
nestling_growth_app-0.1.10.dist-info/entry_points.txt
nestling_growth_app-0.1.10.dist-info/top_level.txt
nestling_growth_app-0.1.10.dist-info/RECORD
